flickr2markdown
