Metadata-Version: 1.1
Name: flickr2markdown
Version: 0.3
Summary: A tool to get a number of flickr uploads or single pictures and create markdown strings out of them
Home-page: https://github.com/xsteadfastx/flickr2markdown
Author: Marvin Steadfast
Author-email: marvin@xsteadfastx.org
License: MIT
Keywords: markdown,flickr
Platform: any
Classifier: Environment :: Console
Classifier: License :: OSI Approved :: MIT License
Classifier: Programming Language :: Python :: 3
